SpringCloudRumenjiaochengCYuyanBianchengWang/README.md
SpringCloudRumenjiaochengCYuyanBianchengWang/__init__.py
SpringCloudRumenjiaochengCYuyanBianchengWang/__main__.py
SpringCloudRumenjiaochengCYuyanBianchengWang/file.epub
SpringCloudRumenjiaochengCYuyanBianchengWang/index.html
SpringCloudRumenjiaochengCYuyanBianchengWang/css/__init__.py
SpringCloudRumenjiaochengCYuyanBianchengWang/css/annotations.css
SpringCloudRumenjiaochengCYuyanBianchengWang/css/main.css
SpringCloudRumenjiaochengCYuyanBianchengWang/css/normalize.css
SpringCloudRumenjiaochengCYuyanBianchengWang/css/popup.css
SpringCloudRumenjiaochengCYuyanBianchengWang/font/__init__.py
SpringCloudRumenjiaochengCYuyanBianchengWang/font/fontello.eot
SpringCloudRumenjiaochengCYuyanBianchengWang/font/fontello.svg
SpringCloudRumenjiaochengCYuyanBianchengWang/font/fontello.ttf
SpringCloudRumenjiaochengCYuyanBianchengWang/font/fontello.woff
SpringCloudRumenjiaochengCYuyanBianchengWang/img/__init__.py
SpringCloudRumenjiaochengCYuyanBianchengWang/img/annotator-glyph-sprite.png
SpringCloudRumenjiaochengCYuyanBianchengWang/img/annotator-icon-sprite.png
SpringCloudRumenjiaochengCYuyanBianchengWang/img/apple-touch-icon.png
SpringCloudRumenjiaochengCYuyanBianchengWang/img/cancelfullscreen.png
SpringCloudRumenjiaochengCYuyanBianchengWang/img/close.png
SpringCloudRumenjiaochengCYuyanBianchengWang/img/fullscreen.png
SpringCloudRumenjiaochengCYuyanBianchengWang/img/loader.gif
SpringCloudRumenjiaochengCYuyanBianchengWang/img/menu-icon.png
SpringCloudRumenjiaochengCYuyanBianchengWang/img/save.png
SpringCloudRumenjiaochengCYuyanBianchengWang/img/saved.png
SpringCloudRumenjiaochengCYuyanBianchengWang/img/settings-s.png
SpringCloudRumenjiaochengCYuyanBianchengWang/img/settings.png
SpringCloudRumenjiaochengCYuyanBianchengWang/img/star.png
SpringCloudRumenjiaochengCYuyanBianchengWang/js/__init__.py
SpringCloudRumenjiaochengCYuyanBianchengWang/js/epub.js
SpringCloudRumenjiaochengCYuyanBianchengWang/js/epub.min.js
spring_cloud_rumenjiaocheng_c_yuyan_biancheng_wang-2024.3.5.0.dist-info/METADATA
spring_cloud_rumenjiaocheng_c_yuyan_biancheng_wang-2024.3.5.0.dist-info/WHEEL
spring_cloud_rumenjiaocheng_c_yuyan_biancheng_wang-2024.3.5.0.dist-info/entry_points.txt
spring_cloud_rumenjiaocheng_c_yuyan_biancheng_wang-2024.3.5.0.dist-info/top_level.txt
spring_cloud_rumenjiaocheng_c_yuyan_biancheng_wang-2024.3.5.0.dist-info/RECORD
